servicenow_cmdb_syncpack/__init__.py
servicenow_cmdb_syncpack/meta.json
servicenow_cmdb_syncpack/apps/CreateServiceNowCI.json
servicenow_cmdb_syncpack/apps/Device_Sync_ScienceLogic_To_ServiceNow.json
servicenow_cmdb_syncpack/apps/Interface_Sync_ScienceLogic_To_ServiceNow.json
servicenow_cmdb_syncpack/apps/bulk_delete_devices.json
servicenow_cmdb_syncpack/apps/cache_CIs_and_DevClasses.json
servicenow_cmdb_syncpack/apps/create_discovery_session.json
servicenow_cmdb_syncpack/apps/create_virtual_device.json
servicenow_cmdb_syncpack/apps/delete_devices.json
servicenow_cmdb_syncpack/apps/generate_relations.json
servicenow_cmdb_syncpack/apps/missing_classes.json
servicenow_cmdb_syncpack/apps/poll_discovery_sessions.json
servicenow_cmdb_syncpack/apps/post_attribute_db_calls.json
servicenow_cmdb_syncpack/apps/post_attribute_rest_calls.json
servicenow_cmdb_syncpack/apps/post_companies_to_snow.json
servicenow_cmdb_syncpack/apps/post_discovery_templates.json
servicenow_cmdb_syncpack/apps/post_import_discovery_dependent.json
servicenow_cmdb_syncpack/apps/post_installed_software_to_snow.json
servicenow_cmdb_syncpack/apps/post_org_company_updates.json
servicenow_cmdb_syncpack/apps/post_org_to_sl1.json
servicenow_cmdb_syncpack/apps/pre_discovery_sync.json
servicenow_cmdb_syncpack/apps/process_discovery_requests.json
servicenow_cmdb_syncpack/apps/process_remove_requests.json
servicenow_cmdb_syncpack/apps/pull_and_post_discovery_logs.json
servicenow_cmdb_syncpack/apps/sync_advanced_topology.json
servicenow_cmdb_syncpack/apps/sync_business_services.json
servicenow_cmdb_syncpack/apps/sync_business_services_to_sl1.json
servicenow_cmdb_syncpack/apps/sync_ci_attributes.json
servicenow_cmdb_syncpack/apps/sync_device_groups.json
servicenow_cmdb_syncpack/apps/sync_discovery_templates.json
servicenow_cmdb_syncpack/apps/sync_filesystems.json
servicenow_cmdb_syncpack/apps/sync_installed_software.json
servicenow_cmdb_syncpack/apps/sync_organizations.json
servicenow_cmdb_syncpack-3.2.1.dev31.dist-info/METADATA
servicenow_cmdb_syncpack-3.2.1.dev31.dist-info/WHEEL
servicenow_cmdb_syncpack-3.2.1.dev31.dist-info/top_level.txt
servicenow_cmdb_syncpack-3.2.1.dev31.dist-info/RECORD
